LICENSE.rst
MANIFEST.in
README.rst
setup.py
misago05redirects/__init__.py
misago05redirects/models.py
misago05redirects/urls.py
misago05redirects/views.py
misago_05_redirects.egg-info/PKG-INFO
misago_05_redirects.egg-info/SOURCES.txt
misago_05_redirects.egg-info/dependency_links.txt
misago_05_redirects.egg-info/top_level.txt